{"id":"src/App.js","dependencies":[{"name":"/home/akalajzi/dev/rpg-boilerplate/package.json","includedInParent":true,"mtime":1536968671225},{"name":"/home/akalajzi/dev/rpg-boilerplate/.babelrc","includedInParent":true,"mtime":1536957074011},{"name":"react","loc":{"line":2,"column":18},"parent":"/home/akalajzi/dev/rpg-boilerplate/src/App.js","resolved":"/home/akalajzi/dev/rpg-boilerplate/node_modules/react/index.js"},{"name":"react-router-dom","loc":{"line":3,"column":30},"parent":"/home/akalajzi/dev/rpg-boilerplate/src/App.js","resolved":"/home/akalajzi/dev/rpg-boilerplate/node_modules/react-router-dom/es/index.js"}],"generated":{"js":"\"use strict\";\n\nObject.defineProperty(exports, \"__esModule\", {\n  value: true\n});\n\nvar _react = require(\"react\");\n\nvar _react2 = _interopRequireDefault(_react);\n\nvar _reactRouterDom = require(\"react-router-dom\");\n\nfunction _interopRequireDefault(obj) { return obj && obj.__esModule ? obj : { default: obj }; }\n\n//  strict\nvar App = function App() {\n  return _react2.default.createElement(\n    _reactRouterDom.BrowserRouter,\n    null,\n    _react2.default.createElement(\n      \"div\",\n      null,\n      \"asdf\"\n    )\n  );\n};\n\nexports.default = App;","map":{"mappings":[{"generated":{"line":7,"column":0},"source":"src/App.js","original":{"line":2,"column":0}},{"generated":{"line":11,"column":0},"source":"src/App.js","original":{"line":3,"column":0}},{"generated":{"line":15,"column":0},"source":"src/App.js","original":{"line":1,"column":0}},{"generated":{"line":16,"column":0},"source":"src/App.js","original":{"line":6,"column":0}},{"name":"App","generated":{"line":16,"column":4},"source":"src/App.js","original":{"line":6,"column":6}},{"generated":{"line":16,"column":10},"source":"src/App.js","original":{"line":6,"column":12}},{"name":"App","generated":{"line":16,"column":19},"source":"src/App.js","original":{"line":6,"column":6}},{"generated":{"line":16,"column":22},"source":"src/App.js","original":{"line":6,"column":12}},{"generated":{"line":16,"column":25},"source":"src/App.js","original":{"line":6,"column":18}},{"generated":{"line":17,"column":0},"source":"src/App.js","original":{"line":7,"column":2}},{"generated":{"line":17,"column":9},"source":"src/App.js","original":{"line":8,"column":4}},{"generated":{"line":18,"column":0},"source":"src/App.js","original":{"line":8,"column":5}},{"generated":{"line":18,"column":33},"source":"src/App.js","original":{"line":8,"column":4}},{"generated":{"line":19,"column":0},"source":"src/App.js","original":{"line":8,"column":4}},{"generated":{"line":20,"column":0},"source":"src/App.js","original":{"line":9,"column":6}},{"generated":{"line":21,"column":0},"source":"src/App.js","original":{"line":9,"column":6}},{"generated":{"line":22,"column":0},"source":"src/App.js","original":{"line":9,"column":6}},{"generated":{"line":23,"column":0},"source":"src/App.js","original":{"line":9,"column":6}},{"generated":{"line":24,"column":0},"source":"src/App.js","original":{"line":9,"column":6}},{"generated":{"line":25,"column":0},"source":"src/App.js","original":{"line":8,"column":4}},{"generated":{"line":25,"column":3},"source":"src/App.js","original":{"line":7,"column":2}},{"generated":{"line":26,"column":0},"source":"src/App.js","original":{"line":12,"column":1}},{"generated":{"line":26,"column":1},"source":"src/App.js","original":{"line":6,"column":0}},{"name":"App","generated":{"line":28,"column":18},"source":"src/App.js","original":{"line":14,"column":15}}],"sources":{"src/App.js":"// @flow strict\nimport React from \"react\"\nimport { BrowserRouter } from \"react-router-dom\";\n\n\nconst App = () => {\n  return(\n    <BrowserRouter>\n      <div>asdf</div>\n    </BrowserRouter>\n  )\n}\n\nexport default App\n"},"lineCount":null}},"hash":"28961d2cf0b13dfe84c50d4ed11143eb","cacheData":{"env":{}}}